{
  "coc.preferences.formatOnSaveFiletypes": [
    "css",
    "scss",
    "html",
    "javascript",
    "typescript",
    "typescriptreact",
    "javascriptreact",
    "json",
    "python"
  ],
  "coc.preferences.extensionUpdateCheck": "never",
  "coc.preferences.messageLevel": "error",

  "suggest.echodocSupport": true,
  "suggest.maxCompleteItemCount": 20,
  "suggest.noselect": false,
  "diagnostic.errorSign": "_X",
  "diagnostic.infoSign": "_!",
  "diagnostic.warningSign": "_W",

  "languageserver":{
   "clangd": {
     "command": "clangd",
     "rootPatterns": ["compile_flags.txt", "compile_commands.json", ".vim/", ".git/", ".hg/"],
     "filetypes": ["c", "cpp", "objc", "objcpp"]
   }
  },

  "eslint.autoFixOnSave": true,

  "javascript.validate.enable": false,
  "typescript.validate.enable": true,
  "javascript.format.enabled": false,
  "typescript.format.enabled": false,

  "html.filetypes": [
    "javascript",
    "html"
  ],
  "html.format.enable": true,

  "snippets.userSnippetsDirectory": "~/dotfiles/.config/ultisnips/",
  "java.errors.incompleteClasspath.severity": "ignore",

  "python.formatting.autopep8args": []
}
